bottle_pydal.py
bottle_pydal-0.2.4.dist-info/DESCRIPTION.rst
bottle_pydal-0.2.4.dist-info/METADATA
bottle_pydal-0.2.4.dist-info/RECORD
bottle_pydal-0.2.4.dist-info/WHEEL
bottle_pydal-0.2.4.dist-info/metadata.json
bottle_pydal-0.2.4.dist-info/top_level.txt
