Metadata-Version: 2.0
Name: bottle-pydal
Version: 0.2.4
Summary: PyDAL for bottle - See Github for more info
Home-page: https://github.com/peregrinius/bottle-pydal
Author: James P Burke
Author-email: james.burke1203@gmail.com
License: LGPL v3.0
Platform: UNKNOWN
Classifier: Development Status :: 4 - Beta
Classifier: Framework :: Bottle
Classifier: Intended Audience :: Developers
Classifier: License :: OSI Approved :: GNU Lesser General Public License v3 (LGPLv3)
Classifier: Operating System :: OS Independent
Classifier: Programming Language :: Python
Classifier: Topic :: Internet :: WWW/HTTP :: WSGI :: Application
Requires-Dist: bottle (>=0.9)
Requires-Dist: pydal
